{
  "swagger": "2.0",
  "info": {
    "description": "",
    "title": "standard public schema",
    "version": "13.0.5"
  },
  "basePath": "/",
  "schemes": [
    "https"
  ],
  "consumes": [
    "application/json",
    "application/vnd.pgrst.object+json;nulls=stripped",
    "application/vnd.pgrst.object+json",
    "text/csv"
  ],
  "produces": [
    "application/json",
    "application/vnd.pgrst.object+json;nulls=stripped",
    "application/vnd.pgrst.object+json",
    "text/csv"
  ],
  "paths": {
    "/": {
      "get": {
        "produces": [
          "application/openapi+json",
          "application/json"
        ],
        "responses": {
          "200": {
            "description": "OK"
          }
        },
        "summary": "OpenAPI description (this document)",
        "tags": [
          "Introspection"
        ]
      }
    },

    "/spot": {
      "get": {
        "parameters": [
          {"$ref": "#/parameters/rowFilter.spot.id_spot"},
          {"$ref": "#/parameters/rowFilter.spot.id_usuario_creador"},
          {"$ref": "#/parameters/rowFilter.spot.id_ubicacion"},
          {"$ref": "#/parameters/rowFilter.spot.nombre"},
          {"$ref": "#/parameters/rowFilter.spot.descripcion"},
          {"$ref": "#/parameters/select"},
          {"$ref": "#/parameters/order"},
          {"$ref": "#/parameters/range"},
          {"$ref": "#/parameters/rangeUnit"},
          {"$ref": "#/parameters/offset"},
          {"$ref": "#/parameters/limit"},
          {"$ref": "#/parameters/preferCount"}
        ],
        "responses": {
          "200": {
            "description": "OK. Returns a list of stargazing spots.",
            "schema": {
              "items": {"$ref": "#/definitions/spot"},
              "type": "array"
            },
            "examples": {
              "application/json": [
                {
                  "id_spot": 1,
                  "id_usuario_creador": 10,
                  "id_ubicacion": 3,
                  "nombre": "Mirador del Teide",
                  "descripcion": "High-altitude viewpoint on Tenerife (approx. 2,300 m). Very low light pollution and excellent horizon visibility. Ideal for astrophotography; dress warmly at night."
                },
                {
                  "id_spot": 2,
                  "id_usuario_creador": 11,
                  "id_ubicacion": 12,
                  "nombre": "Montsec Astronomical Park",
                  "descripcion": "Certified Starlight Reserve with an observatory and public viewing areas. Outstanding sky quality, especially in winter and summer evenings."
                },
                {
                  "id_spot": 3,
                  "id_usuario_creador": 12,
                  "id_ubicacion": 21,
                  "nombre": "Cabo de Gata - Playa de los Genoveses",
                  "descripcion": "Coastal dark-sky beach with a wide southern horizon; good for summer stargazing. Limited facilities and seasonal access restrictions may apply."
                }
              ]
            }
          },
          "206": {"description": "Partial Content"}
        },
        "tags": ["spot"]
      },
      "post": {
        "parameters": [
          {"$ref": "#/parameters/body.spot"},
          {"$ref": "#/parameters/select"},
          {"$ref": "#/parameters/preferPost"}
        ],
        "responses": {
          "201": {
            "description": "Created. Returns the created stargazing spot.",
            "schema": {"$ref": "#/definitions/spot"},
            "examples": {
              "application/json": {
                "id_spot": 15,
                "id_usuario_creador": 10,
                "id_ubicacion": 45,
                "nombre": "Sierra de Guadarrama - Mirador",
                "descripcion": "Mountain viewpoint (~1,800 m) with wide horizons; popular for winter constellation observing and meteor showers. Access by car; check snow conditions in winter."
              }
            }
          }
        },
        "tags": ["spot"]
      },
      "patch": {
        "parameters": [
          {"$ref": "#/parameters/rowFilter.spot.id_spot"},
          {"$ref": "#/parameters/rowFilter.spot.id_usuario_creador"},
          {"$ref": "#/parameters/rowFilter.spot.id_ubicacion"},
          {"$ref": "#/parameters/rowFilter.spot.nombre"},
          {"$ref": "#/parameters/rowFilter.spot.descripcion"},
          {"$ref": "#/parameters/body.spot"},
          {"$ref": "#/parameters/preferReturn"}
        ],
        "responses": {
          "204": {"description": "No Content. Update accepted."},
          "200": {
            "description": "Optional: returns updated resource when Prefer: return=representation is used.",
            "schema": {"$ref": "#/definitions/spot"},
            "examples": {
              "application/json": {
                "id_spot": 1,
                "id_usuario_creador": 10,
                "id_ubicacion": 3,
                "nombre": "Mirador del Teide",
                "descripcion": "High-altitude viewpoint on Tenerife. Updated visitor facilities and improved signage as of 2025; continue to follow local access rules."
              }
            }
          }
        },
        "tags": ["spot"]
      },
      "delete": {
        "parameters": [
          {"$ref": "#/parameters/rowFilter.spot.id_spot"},
          {"$ref": "#/parameters/rowFilter.spot.id_usuario_creador"},
          {"$ref": "#/parameters/rowFilter.spot.id_ubicacion"},
          {"$ref": "#/parameters/rowFilter.spot.nombre"},
          {"$ref": "#/parameters/rowFilter.spot.descripcion"},
          {"$ref": "#/parameters/preferReturn"}
        ],
        "responses": {
          "204": {"description": "No Content. Spot deleted."}
        },
        "tags": ["spot"]
    },
  "/fase_lunar": {
      "get": {
        "parameters": [
          { "$ref": "#/parameters/rowFilter.fase_lunar.id_luna" },
          { "$ref": "#/parameters/rowFilter.fase_lunar.id_ubicacion" },
          { "$ref": "#/parameters/rowFilter.fase_lunar.fase" },
          { "$ref": "#/parameters/rowFilter.fase_lunar.porcentaje_iluminacion" },
          { "$ref": "#/parameters/rowFilter.fase_lunar.fecha" },
          { "$ref": "#/parameters/select" },
          { "$ref": "#/parameters/order" },
          { "$ref": "#/parameters/range" },
          { "$ref": "#/parameters/rangeUnit" },
          { "$ref": "#/parameters/offset" },
          { "$ref": "#/parameters/limit" },
          { "$ref": "#/parameters/preferCount" }
        ],
        "responses": {
          "200": {
            "description": "OK",
            "schema": {
              "type": "array",
              "items": { "$ref": "#/definitions/fase_lunar" },
              "example": [
                {
                  "id_luna": 1,
                  "id_ubicacion": 1,
                  "fase": "Luna llena",
                  "porcentaje_iluminacion": 100.00,
                  "edad_lunar": 15.00,
                  "hora_salida": "18:45:00",
                  "azimut_salida": 96.32,
                  "hora_puesta": "06:55:00",
                  "azimut_puesta": 263.47,
                  "altitud_actual": 65.20,
                  "proxima_fase": "Cuarto menguante",
                  "fecha_proxima_fase": "2025-10-24",
                  "fecha": "2025-10-17"
                }
              ]
            }
          },
          "206": { "description": "Partial Content" }
        },
        "tags": [ "fase_lunar" ]
      },
      "post": {
        "parameters": [
          { "$ref": "#/parameters/body.fase_lunar" },
          { "$ref": "#/parameters/select" },
          { "$ref": "#/parameters/preferPost" }
        ],
        "responses": {
          "201": {
            "description": "Created",
            "examples": {
              "application/json": {
                "id_ubicacion": 1,
                "fase": "Luna nueva",
                "porcentaje_iluminacion": 0.00,
                "edad_lunar": 0.00,
                "hora_salida": "07:46:00",
                "azimut_salida": 90.25,
                "hora_puesta": "19:34:00",
                "azimut_puesta": 270.40,
                "altitud_actual": 0.00,
                "proxima_fase": "Cuarto creciente",
                "fecha_proxima_fase": "2025-10-09",
                "fecha": "2025-10-02"
              }
            }
          }
        },
        "tags": [ "fase_lunar" ]
      },
      "delete": {
        "parameters": [
          { "$ref": "#/parameters/rowFilter.fase_lunar.id_luna" },
          { "$ref": "#/parameters/rowFilter.fase_lunar.id_ubicacion" },
          { "$ref": "#/parameters/rowFilter.fase_lunar.fase" },
          { "$ref": "#/parameters/rowFilter.fase_lunar.porcentaje_iluminacion" },
          { "$ref": "#/parameters/rowFilter.fase_lunar.fecha" },
          { "$ref": "#/parameters/preferReturn" }
        ],
        "responses": {
          "204": {
            "description": "No Content",
            "examples": {
              "application/json": { "message": "Fase lunar eliminada correctamente" }
            }
          }
        },
        "tags": [ "fase_lunar" ]
      },
      "patch": {
        "parameters": [
          { "$ref": "#/parameters/rowFilter.fase_lunar.id_luna" },
          { "$ref": "#/parameters/rowFilter.fase_lunar.id_ubicacion" },
          { "$ref": "#/parameters/rowFilter.fase_lunar.fase" },
          { "$ref": "#/parameters/rowFilter.fase_lunar.porcentaje_iluminacion" },
          { "$ref": "#/parameters/rowFilter.fase_lunar.fecha" },
          { "$ref": "#/parameters/body.fase_lunar" },
          { "$ref": "#/parameters/preferReturn" }
        ],
        "responses": {
          "204": {
            "description": "No Content",
            "examples": {
              "application/json": { "porcentaje_iluminacion": 99.85, "mensaje": "Actualización correcta" }
            }
          }
        },
        "tags": [ "fase_lunar" ]
      }
    },
    "/valoracion": {
      "get": {
        "parameters": [
          {
            "$ref": "#/parameters/rowFilter.valoracion.id_usuario"
          },
          {
            "$ref": "#/parameters/rowFilter.valoracion.id_spot"
          },
          {
            "$ref": "#/parameters/rowFilter.valoracion.puntuacion"
          },
          {
            "$ref": "#/parameters/rowFilter.valoracion.fecha_valoracion"
          },
          {
            "$ref": "#/parameters/select"
          },
          {
            "$ref": "#/parameters/order"
          },
          {
            "$ref": "#/parameters/range"
          },
          {
            "$ref": "#/parameters/rangeUnit"
          },
          {
            "$ref": "#/parameters/offset"
          },
          {
            "$ref": "#/parameters/limit"
          },
          {
            "$ref": "#/parameters/preferCount"
          }
        ],
        "responses": {
          "200": {
            "description": "OK",
            "schema": {
              "items": {
                "$ref": "#/definitions/valoracion"
              },
              "type": "array"
            }
          },
          "206": {
            "description": "Partial Content"
          }
        },
        "tags": [
          "valoracion"
        ]
      },
      "post": {
        "parameters": [
          {
            "$ref": "#/parameters/body.valoracion"
          },
          {
            "$ref": "#/parameters/select"
          },
          {
            "$ref": "#/parameters/preferPost"
          }
        ],
        "responses": {
          "201": {
            "description": "Created"
          }
        },
        "tags": [
          "valoracion"
        ]
      },
      "delete": {
        "parameters": [
          {
            "$ref": "#/parameters/rowFilter.valoracion.id_usuario"
          },
          {
            "$ref": "#/parameters/rowFilter.valoracion.id_spot"
          },
          {
            "$ref": "#/parameters/rowFilter.valoracion.puntuacion"
          },
          {
            "$ref": "#/parameters/rowFilter.valoracion.fecha_valoracion"
          },
          {
            "$ref": "#/parameters/preferReturn"
          }
        ],
        "responses": {
          "204": {
            "description": "No Content"
          }
        },
        "tags": [
          "valoracion"
        ]
      },
      "patch": {
        "parameters": [
          {
            "$ref": "#/parameters/rowFilter.valoracion.id_usuario"
          },
          {
            "$ref": "#/parameters/rowFilter.valoracion.id_spot"
          },
          {
            "$ref": "#/parameters/rowFilter.valoracion.puntuacion"
          },
          {
            "$ref": "#/parameters/rowFilter.valoracion.fecha_valoracion"
          },
          {
            "$ref": "#/parameters/body.valoracion"
          },
          {
            "$ref": "#/parameters/preferReturn"
          }
        ],
        "responses": {
          "204": {
            "description": "No Content"
          }
        },
        "tags": [
          "valoracion"
        ]
      }
    },
    "/usuarioubicacion": {
      "get": {
        "parameters": [
          { "$ref": "#/parameters/rowFilter.usuarioubicacion.id_usuario" },
          { "$ref": "#/parameters/rowFilter.usuarioubicacion.id_ubicacion" },
          { "$ref": "#/parameters/rowFilter.usuarioubicacion.fecha_registro" },
          { "$ref": "#/parameters/select" },
          { "$ref": "#/parameters/order" },
          { "$ref": "#/parameters/range" },
          { "$ref": "#/parameters/rangeUnit" },
          { "$ref": "#/parameters/offset" },
          { "$ref": "#/parameters/limit" },
          { "$ref": "#/parameters/preferCount" }
        ],
        "responses": {
          "200": {
            "description": "OK. Returns user-location associations.",
            "schema": { "type": "array", "items": { "$ref": "#/definitions/usuarioubicacion" } },
            "examples": {
              "application/json": [
                { "id_usuario": 42, "id_ubicacion": 1, "fecha_registro": "2025-10-08" }
              ]
            },
            "x-examples": {
              "sampleAssociations": [
                { "id_usuario": 42, "id_ubicacion": 1, "fecha_registro": "2025-10-08" },
                { "id_usuario": 43, "id_ubicacion": 10, "fecha_registro": "2025-09-01" }
              ]
            }
          }
        },
        "tags": ["usuarioubicacion"]
      },
      "post": {
        "parameters": [
          {
            "name": "usuarioubicacion",
            "in": "body",
            "description": "User-location association object to create",
            "required": true,
            "schema": { "$ref": "#/definitions/usuarioubicacion" },
            "examples": {
              "application/json": { "id_usuario": 42, "id_ubicacion": 1, "fecha_registro": "2025-10-08" }
            },
            "x-examples": {
              "linkUserToPlace": { "id_usuario": 42, "id_ubicacion": 1, "fecha_registro": "2025-10-08" }
            }
          },
          { "$ref": "#/parameters/select" },
          { "$ref": "#/parameters/preferPost" }
        ],
        "responses": {
          "201": {
            "description": "Created. Returns the created association.",
            "schema": { "$ref": "#/definitions/usuarioubicacion" },
            "examples": { "application/json": { "id_usuario": 42, "id_ubicacion": 1, "fecha_registro": "2025-10-08" } }
          }
        },
        "tags": ["usuarioubicacion"]
      },
      "patch": {
        "parameters": [
          { "$ref": "#/parameters/rowFilter.usuarioubicacion.id_usuario" },
          { "$ref": "#/parameters/rowFilter.usuarioubicacion.id_ubicacion" },
          {
            "name": "usuarioubicacion",
            "in": "body",
            "description": "Fields to update for the user-location association",
            "required": true,
            "schema": { "$ref": "#/definitions/usuarioubicacion" },
            "examples": { "application/json": { "fecha_registro": "2025-10-09" } },
            "x-examples": { "updateDate": { "fecha_registro": "2025-10-09" } }
          },
          { "$ref": "#/parameters/preferReturn" }
        ],
        "responses": {
          "204": { "description": "No Content. Update accepted." },
          "200": { "description": "Optional: returns updated resource when `Prefer: return=representation` is used." }
        },
        "tags": ["usuarioubicacion"]
      },
      "delete": {
        "parameters": [
          { "$ref": "#/parameters/rowFilter.usuarioubicacion.id_usuario" },
          { "$ref": "#/parameters/rowFilter.usuarioubicacion.id_ubicacion" },
          { "$ref": "#/parameters/preferReturn" }
        ],
        "responses": {
          "204": { "description": "No Content. Resource deleted." },
          "200": { "description": "Optional: returns deleted resource when `Prefer: return=representation` is used." }
        },
        "tags": ["usuarioubicacion"]
      }
    },
    "/ubicacion": {
      "get": {
        "parameters": [
          { "$ref": "#/parameters/rowFilter.ubicacion.id_ubicacion" },
          { "$ref": "#/parameters/rowFilter.ubicacion.latitud" },
          { "$ref": "#/parameters/rowFilter.ubicacion.longitud" },
          { "$ref": "#/parameters/rowFilter.ubicacion.nombre" },
          { "$ref": "#/parameters/rowFilter.ubicacion.pais" },
          { "$ref": "#/parameters/select" },
          { "$ref": "#/parameters/order" },
          { "$ref": "#/parameters/range" },
          { "$ref": "#/parameters/rangeUnit" },
          { "$ref": "#/parameters/offset" },
          { "$ref": "#/parameters/limit" },
          { "$ref": "#/parameters/preferCount" }
        ],
        "responses": {
          "200": {
            "description": "OK. Returns a list of locations.",
            "schema": { "type": "array", "items": { "$ref": "#/definitions/ubicacion" } },
            "examples": {
              "application/json": [
                { "id_ubicacion": 1, "latitud": 40.416775, "longitud": -3.70379, "nombre": "Retiro Park", "pais": "Spain" },
                { "id_ubicacion": 10, "latitud": 41.000, "longitud": -0.000, "nombre": "Zaragoza", "pais": "Spain" }
              ]
            },
            "x-examples": {
              "sampleList": [
                {
                  "id_ubicacion": 1,
                  "latitud": 40.416775,
                  "longitud": -3.70379,
                  "nombre": "Retiro Park",
                  "pais": "Spain"
                },
                {
                  "id_ubicacion": 10,
                  "latitud": 41.000,
                  "longitud": -0.000,
                  "nombre": "Zaragoza",
                  "pais": "Spain"
                }
              ]
            }
          }
        },
        "tags": ["ubicacion"]
      },
      "post": {
        "parameters": [
          {
            "name": "ubicacion",
            "in": "body",
            "description": "Location object to create",
            "required": true,
            "schema": { "$ref": "#/definitions/ubicacion" },
            "examples": {
              "application/json": { "latitud": 40.416775, "longitud": -3.70379, "nombre": "New Spot", "pais": "Spain" }
            },
            "x-examples": {
              "createMinimal": { "latitud": 40.416775, "longitud": -3.70379, "nombre": "New Spot", "pais": "Spain" },
              "createAtSea": { "latitud": 36.0, "longitud": -5.0, "nombre": "Coastal View", "pais": "Spain" }
            }
          },
          { "$ref": "#/parameters/select" },
          { "$ref": "#/parameters/preferPost" }
        ],
        "responses": {
          "201": {
            "description": "Created. Returns the created location.",
            "schema": { "$ref": "#/definitions/ubicacion" },
            "examples": {
              "application/json": { "id_ubicacion": 123, "latitud": 40.416775, "longitud": -3.70379, "nombre": "New Spot", "pais": "Spain" }
            },
            "x-examples": {
              "createdExample": { "id_ubicacion": 123, "latitud": 40.416775, "longitud": -3.70379, "nombre": "New Spot", "pais": "Spain" }
            }
          }
        },
        "tags": ["ubicacion"]
      },
      "patch": {
        "parameters": [
          { "$ref": "#/parameters/rowFilter.ubicacion.id_ubicacion" },
          {
            "name": "ubicacion",
            "in": "body",
            "description": "Fields to update for a location (partial object)",
            "required": true,
            "schema": { "$ref": "#/definitions/ubicacion" },
            "examples": {
              "application/json": { "nombre": "Retiro Park - East", "pais": "Spain" }
            },
            "x-examples": {
              "rename": { "nombre": "Retiro Park - East" },
              "move": { "latitud": 40.417000, "longitud": -3.704000 }
            }
          },
          { "$ref": "#/parameters/preferReturn" }
        ],
        "responses": {
          "204": { "description": "No Content. Update accepted." },
          "200": {
            "description": "Optional: returns updated resource when `Prefer: return=representation` is used.",
            "schema": { "$ref": "#/definitions/ubicacion" },
            "examples": {
              "application/json": { "id_ubicacion": 1, "latitud": 40.417000, "longitud": -3.704000, "nombre": "Retiro Park - East", "pais": "Spain" }
            }
          }
        },
        "tags": ["ubicacion"]
      },
      "delete": {
        "parameters": [
          { "$ref": "#/parameters/rowFilter.ubicacion.id_ubicacion" },
          { "$ref": "#/parameters/preferReturn" }
        ],
        "responses": {
          "204": { "description": "No Content. Resource deleted." },
          "200": {
            "description": "Optional: returns deleted resource when `Prefer: return=representation` is used.",
            "schema": { "$ref": "#/definitions/ubicacion" },
            "examples": {
              "application/json": { "id_ubicacion": 10, "latitud": 41.0, "longitud": -0.0, "nombre": "Alagón", "pais": "Spain" }
            }
          }
        },
        "tags": ["ubicacion"]
      }
    },
    "/usuariogrupo": {
      "get": {
        "parameters": [
          {
            "$ref": "#/parameters/rowFilter.usuariogrupo.id_usuario"
          },
          {
            "$ref": "#/parameters/rowFilter.usuariogrupo.id_grupo"
          },
          {
            "$ref": "#/parameters/rowFilter.usuariogrupo.propietario"
          },
          {
            "$ref": "#/parameters/rowFilter.usuariogrupo.fecha_union"
          },
          {
            "$ref": "#/parameters/select"
          },
          {
            "$ref": "#/parameters/order"
          },
          {
            "$ref": "#/parameters/range"
          },
          {
            "$ref": "#/parameters/rangeUnit"
          },
          {
            "$ref": "#/parameters/offset"
          },
          {
            "$ref": "#/parameters/limit"
          },
          {
            "$ref": "#/parameters/preferCount"
          }
        ],
        "responses": {
          "200": {
            "description": "OK",
            "schema": {
              "items": {
                "$ref": "#/definitions/usuariogrupo"
              },
              "type": "array"
            }
          },
          "206": {
            "description": "Partial Content"
          }
        },
        "tags": [
          "usuariogrupo"
        ]
      },
      "post": {
        "parameters": [
          {
            "$ref": "#/parameters/body.usuariogrupo"
          },
          {
            "$ref": "#/parameters/select"
          },
          {
            "$ref": "#/parameters/preferPost"
          }
        ],
        "responses": {
          "201": {
            "description": "Created"
          }
        },
        "tags": [
          "usuariogrupo"
        ]
      },
      "delete": {
        "parameters": [
          {
            "$ref": "#/parameters/rowFilter.usuariogrupo.id_usuario"
          },
          {
            "$ref": "#/parameters/rowFilter.usuariogrupo.id_grupo"
          },
          {
            "$ref": "#/parameters/rowFilter.usuariogrupo.propietario"
          },
          {
            "$ref": "#/parameters/rowFilter.usuariogrupo.fecha_union"
          },
          {
            "$ref": "#/parameters/preferReturn"
          }
        ],
        "responses": {
          "204": {
            "description": "No Content"
          }
        },
        "tags": [
          "usuariogrupo"
        ]
      },
      "patch": {
        "parameters": [
          {
            "$ref": "#/parameters/rowFilter.usuariogrupo.id_usuario"
          },
          {
            "$ref": "#/parameters/rowFilter.usuariogrupo.id_grupo"
          },
          {
            "$ref": "#/parameters/rowFilter.usuariogrupo.propietario"
          },
          {
            "$ref": "#/parameters/rowFilter.usuariogrupo.fecha_union"
          },
          {
            "$ref": "#/parameters/body.usuariogrupo"
          },
          {
            "$ref": "#/parameters/preferReturn"
          }
        ],
        "responses": {
          "204": {
            "description": "No Content"
          }
        },
        "tags": [
          "usuariogrupo"
        ]
      }
    },
    "/grupoobservacion": {
      "get": {
        "parameters": [
          {
            "$ref": "#/parameters/rowFilter.grupoobservacion.id_grupo"
          },
          {
            "$ref": "#/parameters/rowFilter.grupoobservacion.nombre"
          },
          {
            "$ref": "#/parameters/rowFilter.grupoobservacion.descripcion"
          },
          {
            "$ref": "#/parameters/rowFilter.grupoobservacion.fecha_creacion"
          },
          {
            "$ref": "#/parameters/select"
          },
          {
            "$ref": "#/parameters/order"
          },
          {
            "$ref": "#/parameters/range"
          },
          {
            "$ref": "#/parameters/rangeUnit"
          },
          {
            "$ref": "#/parameters/offset"
          },
          {
            "$ref": "#/parameters/limit"
          },
          {
            "$ref": "#/parameters/preferCount"
          }
        ],
        "responses": {
          "200": {
            "description": "OK",
            "schema": {
              "items": {
                "$ref": "#/definitions/grupoobservacion"
              },
              "type": "array"
            }
          },
          "206": {
            "description": "Partial Content"
          }
        },
        "tags": [
          "grupoobservacion"
        ]
      },
      "post": {
        "parameters": [
          {
            "$ref": "#/parameters/body.grupoobservacion"
          },
          {
            "$ref": "#/parameters/select"
          },
          {
            "$ref": "#/parameters/preferPost"
          }
        ],
        "responses": {
          "201": {
            "description": "Created"
          }
        },
        "tags": [
          "grupoobservacion"
        ]
      },
      "delete": {
        "parameters": [
          {
            "$ref": "#/parameters/rowFilter.grupoobservacion.id_grupo"
          },
          {
            "$ref": "#/parameters/rowFilter.grupoobservacion.nombre"
          },
          {
            "$ref": "#/parameters/rowFilter.grupoobservacion.descripcion"
          },
          {
            "$ref": "#/parameters/rowFilter.grupoobservacion.fecha_creacion"
          },
          {
            "$ref": "#/parameters/preferReturn"
          }
        ],
        "responses": {
          "204": {
            "description": "No Content"
          }
        },
        "tags": [
          "grupoobservacion"
        ]
      },
      "patch": {
        "parameters": [
          {
            "$ref": "#/parameters/rowFilter.grupoobservacion.id_grupo"
          },
          {
            "$ref": "#/parameters/rowFilter.grupoobservacion.nombre"
          },
          {
            "$ref": "#/parameters/rowFilter.grupoobservacion.descripcion"
          },
          {
            "$ref": "#/parameters/rowFilter.grupoobservacion.fecha_creacion"
          },
          {
            "$ref": "#/parameters/body.grupoobservacion"
          },
          {
            "$ref": "#/parameters/preferReturn"
          }
        ],
        "responses": {
          "204": {
            "description": "No Content"
          }
        },
        "tags": [
          "grupoobservacion"
        ]
      }
    },
    "/seguidores": {
      "get": {
        "parameters": [
          {
            "$ref": "#/parameters/rowFilter.seguidores.id_seguidor"
          },
          {
            "$ref": "#/parameters/rowFilter.seguidores.id_seguido"
          },
          {
            "$ref": "#/parameters/rowFilter.seguidores.fecha_seguimiento"
          },
          {
            "$ref": "#/parameters/select"
          },
          {
            "$ref": "#/parameters/order"
          },
          {
            "$ref": "#/parameters/range"
          },
          {
            "$ref": "#/parameters/rangeUnit"
          },
          {
            "$ref": "#/parameters/offset"
          },
          {
            "$ref": "#/parameters/limit"
          },
          {
            "$ref": "#/parameters/preferCount"
          }
        ],
        "responses": {
          "200": {
            "description": "OK",
            "schema": {
              "items": {
                "$ref": "#/definitions/seguidores"
              },
              "type": "array"
            }
          },
          "206": {
            "description": "Partial Content"
          }
        },
        "tags": [
          "seguidores"
        ]
      },
      "post": {
        "parameters": [
          {
            "$ref": "#/parameters/body.seguidores"
          },
          {
            "$ref": "#/parameters/select"
          },
          {
            "$ref": "#/parameters/preferPost"
          }
        ],
        "responses": {
          "201": {
            "description": "Created"
          }
        },
        "tags": [
          "seguidores"
        ]
      },
      "delete": {
        "parameters": [
          {
            "$ref": "#/parameters/rowFilter.seguidores.id_seguidor"
          },
          {
            "$ref": "#/parameters/rowFilter.seguidores.id_seguido"
          },
          {
            "$ref": "#/parameters/rowFilter.seguidores.fecha_seguimiento"
          },
          {
            "$ref": "#/parameters/preferReturn"
          }
        ],
        "responses": {
          "204": {
            "description": "No Content"
          }
        },
        "tags": [
          "seguidores"
        ]
      },
      "patch": {
        "parameters": [
          {
            "$ref": "#/parameters/rowFilter.seguidores.id_seguidor"
          },
          {
            "$ref": "#/parameters/rowFilter.seguidores.id_seguido"
          },
          {
            "$ref": "#/parameters/rowFilter.seguidores.fecha_seguimiento"
          },
          {
            "$ref": "#/parameters/body.seguidores"
          },
          {
            "$ref": "#/parameters/preferReturn"
          }
        ],
        "responses": {
          "204": {
            "description": "No Content"
          }
        },
        "tags": [
          "seguidores"
        ]
      }
    },
    "/usuario": {
      "get": {
        "parameters": [
          {
            "$ref": "#/parameters/rowFilter.usuario.id_usuario"
          },
          {
            "$ref": "#/parameters/rowFilter.usuario.nombre_usuario"
          },
          {
            "$ref": "#/parameters/rowFilter.usuario.email"
          },
          {
            "$ref": "#/parameters/rowFilter.usuario.contrasenia_hash"
          },
          {
            "$ref": "#/parameters/rowFilter.usuario.url_foto"
          },
          {
            "$ref": "#/parameters/select"
          },
          {
            "$ref": "#/parameters/order"
          },
          {
            "$ref": "#/parameters/range"
          },
          {
            "$ref": "#/parameters/rangeUnit"
          },
          {
            "$ref": "#/parameters/offset"
          },
          {
            "$ref": "#/parameters/limit"
          },
          {
            "$ref": "#/parameters/preferCount"
          }
        ],
        "responses": {
          "200": {
            "description": "OK",
            "schema": {
              "items": {
                "$ref": "#/definitions/usuario"
              },
              "type": "array"
            }
          },
          "206": {
            "description": "Partial Content"
          }
        },
        "tags": [
          "usuario"
        ]
      },
      "post": {
        "parameters": [
          {
            "$ref": "#/parameters/body.usuario"
          },
          {
            "$ref": "#/parameters/select"
          },
          {
            "$ref": "#/parameters/preferPost"
          }
        ],
        "responses": {
          "201": {
            "description": "Created"
          }
        },
        "tags": [
          "usuario"
        ]
      },
      "delete": {
        "parameters": [
          {
            "$ref": "#/parameters/rowFilter.usuario.id_usuario"
          },
          {
            "$ref": "#/parameters/rowFilter.usuario.nombre_usuario"
          },
          {
            "$ref": "#/parameters/rowFilter.usuario.email"
          },
          {
            "$ref": "#/parameters/rowFilter.usuario.contrasenia_hash"
          },
          {
            "$ref": "#/parameters/rowFilter.usuario.url_foto"
          },
          {
            "$ref": "#/parameters/preferReturn"
          }
        ],
        "responses": {
          "204": {
            "description": "No Content"
          }
        },
        "tags": [
          "usuario"
        ]
      },
      "patch": {
        "parameters": [
          {
            "$ref": "#/parameters/rowFilter.usuario.id_usuario"
          },
          {
            "$ref": "#/parameters/rowFilter.usuario.nombre_usuario"
          },
          {
            "$ref": "#/parameters/rowFilter.usuario.email"
          },
          {
            "$ref": "#/parameters/rowFilter.usuario.contrasenia_hash"
          },
          {
            "$ref": "#/parameters/rowFilter.usuario.url_foto"
          },
          {
            "$ref": "#/parameters/body.usuario"
          },
          {
            "$ref": "#/parameters/preferReturn"
          }
        ],
        "responses": {
          "204": {
            "description": "No Content"
          }
        },
        "tags": [
          "usuario"
        ]
      }
    },
    "/informacion_meteorologica": {
      "get": {
        "parameters": [
          { "$ref": "#/parameters/rowFilter.informacion_meteorologica.id_info_meteorologica" },
          { "$ref": "#/parameters/rowFilter.informacion_meteorologica.id_ubicacion" },
          { "$ref": "#/parameters/rowFilter.informacion_meteorologica.temperatura" },
          { "$ref": "#/parameters/rowFilter.informacion_meteorologica.humedad" },
          { "$ref": "#/parameters/rowFilter.informacion_meteorologica.viento" },
          { "$ref": "#/parameters/rowFilter.informacion_meteorologica.nubosidad" },
          { "$ref": "#/parameters/rowFilter.informacion_meteorologica.contaminacion_luminica" },
          { "$ref": "#/parameters/rowFilter.informacion_meteorologica.indicador_general_sobre_el_cielo" },
          { "$ref": "#/parameters/rowFilter.informacion_meteorologica.ultima_actualizacion" },
          { "$ref": "#/parameters/select" },
          { "$ref": "#/parameters/order" },
          { "$ref": "#/parameters/range" },
          { "$ref": "#/parameters/rangeUnit" },
          { "$ref": "#/parameters/offset" },
          { "$ref": "#/parameters/limit" },
          { "$ref": "#/parameters/preferCount" }
        ],
        "responses": {
          "200": {
            "description": "OK. Returns weather info records.",
            "schema": { "type": "array", "items": { "$ref": "#/definitions/informacion_meteorologica" } },
            "examples": {
              "application/json": [
                { "id_info_meteorologica": 5, "id_ubicacion": 1, "temperatura": 12.3, "humedad": 68, "viento": 3.4, "nubosidad": 20, "contaminacion_luminica": 18.5, "indicador_general_sobre_el_cielo": 7.8, "ultima_actualizacion": "2025-10-08T21:30:00Z" }
              ]
            },
            "x-examples": {
              "recentReadings": [
                { "id_info_meteorologica": 5, "id_ubicacion": 1, "temperatura": 12.3, "humedad": 68, "viento": 3.4, "nubosidad": 20, "contaminacion_luminica": 18.5, "indicador_general_sobre_el_cielo": 7.8, "ultima_actualizacion": "2025-10-08T21:30:00Z" },
                { "id_info_meteorologica": 6, "id_ubicacion": 2, "temperatura": 7.0, "humedad": 82, "viento": 1.2, "nubosidad": 10, "contaminacion_luminica": 20.0, "indicador_general_sobre_el_cielo": 8.2, "ultima_actualizacion": "2025-10-08T20:00:00Z" }
              ]
            }
          }
        },
        "tags": ["informacion_meteorologica"]
      },
      "post": {
        "parameters": [
          {
            "name": "informacion_meteorologica",
            "in": "body",
            "description": "Weather information object to insert",
            "required": true,
            "schema": { "$ref": "#/definitions/informacion_meteorologica" },
            "examples": {
              "application/json": { "id_ubicacion": 1, "temperatura": 10.5, "humedad": 75, "viento": 2.1, "nubosidad": 15, "contaminacion_luminica": 17.0, "indicador_general_sobre_el_cielo": 8.0 }
            },
            "x-examples": {
              "typicalReading": { "id_ubicacion": 1, "temperatura": 10.5, "humedad": 75, "viento": 2.1, "nubosidad": 15, "contaminacion_luminica": 17.0, "indicador_general_sobre_el_cielo": 8.0 },
              "nightReading": { "id_ubicacion": 1, "temperatura": 6.2, "humedad": 90, "viento": 0.5, "nubosidad": 5, "contaminacion_luminica": 18.2, "indicador_general_sobre_el_cielo": 9.0 }
            }
          },
          { "$ref": "#/parameters/select" },
          { "$ref": "#/parameters/preferPost" }
        ],
        "responses": {
          "201": {
            "description": "Created. Returns created weather info.",
            "schema": { "$ref": "#/definitions/informacion_meteorologica" },
            "examples": {
              "application/json": { "id_info_meteorologica": 77, "id_ubicacion": 1, "temperatura": 10.5, "humedad": 75, "viento": 2.1, "nubosidad": 15, "contaminacion_luminica": 17.0, "indicador_general_sobre_el_cielo": 8.0, "ultima_actualizacion": "2025-10-08T21:35:00Z" }
            }
          }
        },
        "tags": ["informacion_meteorologica"]
      },
      "patch": {
        "parameters": [
          { "$ref": "#/parameters/rowFilter.informacion_meteorologica.id_info_meteorologica" },
          {
            "name": "informacion_meteorologica",
            "in": "body",
            "description": "Fields to update for weather info (partial object)",
            "required": true,
            "schema": { "$ref": "#/definitions/informacion_meteorologica" },
            "examples": {
              "application/json": { "temperatura": 11.0, "humedad": 70 }
            },
            "x-examples": {
              "updateTemp": { "temperatura": 11.0 },
              "updateWindClouds": { "viento": 4.2, "nubosidad": 30 }
            }
          },
          { "$ref": "#/parameters/preferReturn" }
        ],
        "responses": {
          "204": { "description": "No Content. Update accepted." },
          "200": {
            "description": "Optional: returns updated resource when `Prefer: return=representation` is used.",
            "schema": { "$ref": "#/definitions/informacion_meteorologica" },
            "examples": { "application/json": { "id_info_meteorologica": 77, "id_ubicacion": 1, "temperatura": 11.0, "humedad": 70, "viento": 2.1, "nubosidad": 15, "contaminacion_luminica": 17.0, "indicador_general_sobre_el_cielo": 8.0 } }
          }
        },
        "tags": ["informacion_meteorologica"]
      },
      "delete": {
        "parameters": [
          { "$ref": "#/parameters/rowFilter.informacion_meteorologica.id_info_meteorologica" },
          { "$ref": "#/parameters/preferReturn" }
        ],
        "responses": {
          "204": { "description": "No Content. Resource deleted." },
          "200": { "description": "Optional: returns deleted resource when `Prefer: return=representation` is used." }
        },
        "tags": ["informacion_meteorologica"]
      }
    },
    "/comentario": {
      "get": {
        "parameters": [
          {
            "$ref": "#/parameters/rowFilter.comentario.id_comentario"
          },
          {
            "$ref": "#/parameters/rowFilter.comentario.id_usuario"
          },
          {
            "$ref": "#/parameters/rowFilter.comentario.id_spot"
          },
          {
            "$ref": "#/parameters/rowFilter.comentario.texto"
          },
          {
            "$ref": "#/parameters/rowFilter.comentario.fecha_comentario"
          },
          {
            "$ref": "#/parameters/select"
          },
          {
            "$ref": "#/parameters/order"
          },
          {
            "$ref": "#/parameters/range"
          },
          {
            "$ref": "#/parameters/rangeUnit"
          },
          {
            "$ref": "#/parameters/offset"
          },
          {
            "$ref": "#/parameters/limit"
          },
          {
            "$ref": "#/parameters/preferCount"
          }
        ],
        "responses": {
          "200": {
            "description": "OK",
            "schema": {
              "items": {
                "$ref": "#/definitions/comentario"
              },
              "type": "array"
            }
          },
          "206": {
            "description": "Partial Content"
          }
        },
        "tags": [
          "comentario"
        ]
      },
      "post": {
        "parameters": [
          {
            "$ref": "#/parameters/body.comentario"
          },
          {
            "$ref": "#/parameters/select"
          },
          {
            "$ref": "#/parameters/preferPost"
          }
        ],
        "responses": {
          "201": {
            "description": "Created"
          }
        },
        "tags": [
          "comentario"
        ]
      },
      "delete": {
        "parameters": [
          {
            "$ref": "#/parameters/rowFilter.comentario.id_comentario"
          },
          {
            "$ref": "#/parameters/rowFilter.comentario.id_usuario"
          },
          {
            "$ref": "#/parameters/rowFilter.comentario.id_spot"
          },
          {
            "$ref": "#/parameters/rowFilter.comentario.texto"
          },
          {
            "$ref": "#/parameters/rowFilter.comentario.fecha_comentario"
          },
          {
            "$ref": "#/parameters/preferReturn"
          }
        ],
        "responses": {
          "204": {
            "description": "No Content"
          }
        },
        "tags": [
          "comentario"
        ]
      },
      "patch": {
        "parameters": [
          {
            "$ref": "#/parameters/rowFilter.comentario.id_comentario"
          },
          {
            "$ref": "#/parameters/rowFilter.comentario.id_usuario"
          },
          {
            "$ref": "#/parameters/rowFilter.comentario.id_spot"
          },
          {
            "$ref": "#/parameters/rowFilter.comentario.texto"
          },
          {
            "$ref": "#/parameters/rowFilter.comentario.fecha_comentario"
          },
          {
            "$ref": "#/parameters/body.comentario"
          },
          {
            "$ref": "#/parameters/preferReturn"
          }
        ],
        "responses": {
          "204": {
            "description": "No Content"
          }
        },
        "tags": [
          "comentario"
        ]
      }
    },
    "/cielo_visible": {
      "get": {
        "parameters": [
          { "$ref": "#/parameters/rowFilter.cielo_visible.id_cielo_visible" },
          { "$ref": "#/parameters/rowFilter.cielo_visible.id_ubicacion" },
          { "$ref": "#/parameters/rowFilter.cielo_visible.tipo" },
          { "$ref": "#/parameters/rowFilter.cielo_visible.nombre" },
          { "$ref": "#/parameters/rowFilter.cielo_visible.descripcion" },
          { "$ref": "#/parameters/rowFilter.cielo_visible.ultima_actualizacion" },
          { "$ref": "#/parameters/select" },
          { "$ref": "#/parameters/order" },
          { "$ref": "#/parameters/range" },
          { "$ref": "#/parameters/rangeUnit" },
          { "$ref": "#/parameters/offset" },
          { "$ref": "#/parameters/limit" },
          { "$ref": "#/parameters/preferCount" }
        ],
        "responses": {
          "200": {
            "description": "OK. Returns visible-sky objects.",
            "schema": { "type": "array", "items": { "$ref": "#/definitions/cielo_visible" } },
            "examples": {
              "application/json": [
                { "id_cielo_visible": 7, "id_ubicacion": 1, "tipo": "planet", "nombre": "Jupiter", "descripcion": "Visible after sunset", "ultima_actualizacion": "2025-10-08T21:30:00Z" }
              ]
            },
            "x-examples": {
              "sightings": [
                { "id_cielo_visible": 7, "id_ubicacion": 1, "tipo": "planet", "nombre": "Jupiter", "descripcion": "Visible after sunset", "ultima_actualizacion": "2025-10-08T21:30:00Z" },
                { "id_cielo_visible": 8, "id_ubicacion": 2, "tipo": "constellation", "nombre": "Orion", "descripcion": "High in the sky in winter", "ultima_actualizacion": "2025-10-08T00:00:00Z" }
              ]
            }
          }
        },
        "tags": ["cielo_visible"]
      },
      "/alerta": {
        "get": {
          "parameters": [
            { "$ref": "#/parameters/rowFilter.alerta.id_alerta" },
            { "$ref": "#/parameters/rowFilter.alerta.id_usuario" },
            { "$ref": "#/parameters/rowFilter.alerta.id_ubicacion" },
            { "$ref": "#/parameters/rowFilter.alerta.tipo_alerta" },
            { "$ref": "#/parameters/rowFilter.alerta.tipo_repeticion" },
            { "$ref": "#/parameters/rowFilter.alerta.activa" },
            { "$ref": "#/parameters/select" },
            { "$ref": "#/parameters/order" },
            { "$ref": "#/parameters/range" },
            { "$ref": "#/parameters/rangeUnit" },
            { "$ref": "#/parameters/offset" },
            { "$ref": "#/parameters/limit" },
            { "$ref": "#/parameters/preferCount" }
          ],
          "responses": {
            "200": {
              "description": "OK. Returns a list of alerts for the user.",
              "schema": { "type": "array", "items": { "$ref": "#/definitions/alerta" } },
              "examples": {
                "application/json": [
                  {
                    "id_alerta": 2,
                    "id_usuario": "da8ceff9-3860-483d-ba99-4e8c8b8669d4",
                    "id_ubicacion": 57,
                    "tipo_alerta": "FASE_LUNAR",
                    "parametro_objetivo": "Waxing Crescent",
                    "tipo_repeticion": "UNICA",
                    "fecha_objetivo": null,
                    "hora_objetivo": null,
                    "valor_minimo": null,
                    "valor_maximo": null,
                    "activa": true,
                    "fecha_creacion": "2025-10-21T20:23:57",
                    "ultima_notificacion": null
                  }
                ]
              }
            }
          },
          "tags": ["alerta"]
        },
        "post": {
          "parameters": [
            { "$ref": "#/parameters/body.alerta" },
            { "$ref": "#/parameters/select" },
            { "$ref": "#/parameters/preferPost" }
          ],
          "responses": {
            "201": {
              "description": "Created. Returns the created alert.",
              "schema": { "$ref": "#/definitions/alerta" },
              "examples": {
                "application/json": {
                  "id_alerta": 3,
                  "id_usuario": "da8ceff9-3860-483d-ba99-4e8c8b8669d4",
                  "id_ubicacion": 57,
                  "tipo_alerta": "CONSTELACIONES",
                  "parametro_objetivo": "Orion",
                  "tipo_repeticion": "SEMANAL",
                  "fecha_objetivo": null,
                  "hora_objetivo": "00:00:00",
                  "valor_minimo": null,
                  "valor_maximo": null,
                  "activa": true,
                  "fecha_creacion": "2025-10-22T09:00:00",
                  "ultima_notificacion": null
                }
              }
            }
          },
          "tags": ["alerta"]
        },
        "patch": {
          "parameters": [
            { "$ref": "#/parameters/rowFilter.alerta.id_alerta" },
            { "$ref": "#/parameters/body.alerta" },
            { "$ref": "#/parameters/preferReturn" }
          ],
          "responses": {
            "204": { "description": "No Content. Update accepted." },
            "200": {
              "description": "Optional: returns updated resource when `Prefer: return=representation` is used.",
              "schema": { "$ref": "#/definitions/alerta" },
              "examples": {
                "application/json": {
                  "id_alerta": 2,
                  "id_usuario": "da8ceff9-3860-483d-ba99-4e8c8b8669d4",
                  "id_ubicacion": 57,
                  "tipo_alerta": "FASE_LUNAR",
                  "parametro_objetivo": "Waxing Crescent",
                  "tipo_repeticion": "UNICA",
                  "fecha_objetivo": "2025-10-24",
                  "hora_objetivo": "08:00:00",
                  "valor_minimo": null,
                  "valor_maximo": null,
                  "activa": true,
                  "fecha_creacion": "2025-10-21T20:23:57",
                  "ultima_notificacion": null
                }
              }
            }
          },
          "tags": ["alerta"]
        },
        "delete": {
          "parameters": [
            { "$ref": "#/parameters/rowFilter.alerta.id_alerta" },
            { "$ref": "#/parameters/preferReturn" }
          ],
          "responses": {
            "204": { "description": "No Content. Alert deleted." }
          },
          "tags": ["alerta"]
        }
      },
      "post": {
        "parameters": [
          {
            "name": "cielo_visible",
            "in": "body",
            "description": "Object representing something visible in the sky",
            "required": true,
            "schema": { "$ref": "#/definitions/cielo_visible" },
            "examples": {
              "application/json": { "id_ubicacion": 1, "tipo": "planet", "nombre": "Jupiter", "descripcion": "Visible in the east just after sunset" }
            },
            "x-examples": {
              "planetSighting": { "id_ubicacion": 1, "tipo": "planet", "nombre": "Jupiter", "descripcion": "Visible in the east just after sunset" },
              "meteorShower": { "id_ubicacion": 1, "tipo": "phenomenon", "nombre": "Perseids", "descripcion": "Peak visibility around August 12" }
            }
          },
          { "$ref": "#/parameters/select" },
          { "$ref": "#/parameters/preferPost" }
        ],
        "responses": {
          "201": {
            "description": "Created. Returns created visible-sky object.",
            "schema": { "$ref": "#/definitions/cielo_visible" },
            "examples": {
              "application/json": { "id_cielo_visible": 99, "id_ubicacion": 1, "tipo": "planet", "nombre": "Jupiter", "descripcion": "Visible in the east just after sunset", "ultima_actualizacion": "2025-10-08T21:40:00Z" }
            }
          }
        },
        "tags": ["cielo_visible"]
      },
      "patch": {
        "parameters": [
          { "$ref": "#/parameters/rowFilter.cielo_visible.id_cielo_visible" },
          {
            "name": "cielo_visible",
            "in": "body",
            "description": "Fields to update for a visible-sky record",
            "required": true,
            "schema": { "$ref": "#/definitions/cielo_visible" },
            "examples": {
              "application/json": { "descripcion": "Now visible at low altitude" }
            },
            "x-examples": {
              "updateDescription": { "descripcion": "Now visible at low altitude" },
              "changeType": { "tipo": "satellite", "nombre": "ISS" }
            }
          },
          { "$ref": "#/parameters/preferReturn" }
        ],
        "responses": {
          "204": { "description": "No Content. Update accepted." },
          "200": { "description": "Optional: returns updated resource when `Prefer: return=representation` is used." }
        },
        "tags": ["cielo_visible"]
      },
      "delete": {
        "parameters": [
          { "$ref": "#/parameters/rowFilter.cielo_visible.id_cielo_visible" },
          { "$ref": "#/parameters/preferReturn" }
        ],
        "responses": {
          "204": { "description": "No Content. Resource deleted." },
          "200": { "description": "Optional: returns deleted resource when `Prefer: return=representation` is used." }
        },
        "tags": ["cielo_visible"]
      }
  },
  "definitions": {
    "spot": {
      "required": [
        "id_spot",
        "id_usuario_creador",
        "id_ubicacion",
        "nombre"
      ],
      "properties": {
        "id_spot": {
          "description": "Note:\nThis is a Primary Key.<pk/>",
          "format": "integer",
          "type": "integer"
        },
        "id_usuario_creador": {
          "description": "Note:\nThis is a Foreign Key to `usuario.id_usuario`.<fk table='usuario' column='id_usuario'/>",
          "format": "integer",
          "type": "integer"
        },
        "id_ubicacion": {
          "description": "Note:\nThis is a Foreign Key to `ubicacion.id_ubicacion`.<fk table='ubicacion' column='id_ubicacion'/>",
          "format": "integer",
          "type": "integer"
        },
        "nombre": {
          "format": "character varying",
          "type": "string"
        },
        "descripcion": {
          "format": "text",
          "type": "string"
        }
      },
      "type": "object",
      "example": {
        "id_spot": 1,
        "id_usuario_creador": 10,
        "id_ubicacion": 3,
        "nombre": "Mirador del Teide",
        "descripcion": "High-altitude viewpoint on Tenerife (approx. 2,300 m). Very low light pollution and excellent horizon visibility. Ideal for astrophotography."
      }
    },
    "fase_lunar": {
      "required": [
        "id_luna",
        "fase",
        "fecha"
      ],
      "properties": {
        "id_luna": {
          "description": "Note:\nThis is a Primary Key.<pk/>",
          "format": "integer",
          "type": "integer"
        },
        "id_ubicacion": {
          "description": "Note:\nThis is a Foreign Key to `ubicacion.id_ubicacion`.<fk table='ubicacion' column='id_ubicacion'/>",
          "format": "integer",
          "type": "integer"
        },
        "fase": {
          "format": "character varying",
          "maxLength": 50,
          "type": "string"
        },
        "porcentaje_iluminacion": {
          "format": "numeric",
          "type": "number"
        },
        "fecha": {
          "format": "date",
          "type": "string"
        }
      },
      "type": "object"
    },
    "valoracion": {
      "required": [
        "id_usuario",
        "id_spot"
      ],
      "properties": {
        "id_usuario": {
          "description": "Note:\nThis is a Primary Key.<pk/>\nThis is a Foreign Key to `usuario.id_usuario`.<fk table='usuario' column='id_usuario'/>",
          "format": "integer",
          "type": "integer"
        },
        "id_spot": {
          "description": "Note:\nThis is a Primary Key.<pk/>\nThis is a Foreign Key to `spot.id_spot`.<fk table='spot' column='id_spot'/>",
          "format": "integer",
          "type": "integer"
        },
        "puntuacion": {
          "format": "integer",
          "type": "integer"
        },
        "fecha_valoracion": {
          "format": "date",
          "type": "string"
        }
      },
      "type": "object"
    },
    "usuarioubicacion": {
      "required": ["id_usuario","id_ubicacion"],
      "properties": {
        "id_usuario": {
          "description": "Foreign key to usuario.id_usuario.",
          "format": "integer",
          "type": "integer"
        },
        "id_ubicacion": {
          "description": "Foreign key to ubicacion.id_ubicacion.",
          "format": "integer",
          "type": "integer"
        },
        "fecha_registro": {
          "description": "Registration date of the user-location association (ISO date yyyy-mm-dd or timestamp if used).",
          "format": "date",
          "type": "string"
        }
      },
      "type": "object",
      "example": {
        "id_usuario": 42,
        "id_ubicacion": 1,
        "fecha_registro": "2025-10-08"
      }
    },
    "ubicacion": {
      "required": ["id_ubicacion","latitud","longitud","nombre","pais"],
      "properties": {
        "id_ubicacion": {
          "description": "Primary key for the location record.",
          "format": "integer",
          "type": "integer"
        },
        "latitud": {
          "description": "Latitude in decimal degrees, WGS84. Range: -90 to 90. Unit: degrees.",
          "format": "double precision",
          "type": "number"
        },
        "longitud": {
          "description": "Longitude in decimal degrees, WGS84. Range: -180 to 180. Unit: degrees.",
          "format": "double precision",
          "type": "number"
        },
        "nombre": {
          "description": "Human-readable name for the location (e.g. 'Retiro Park').",
          "type": "string"
        },
        "pais": {
          "description": "Country name or ISO code.",
          "type": "string"
        }
      },
      "type": "object",
      "example": {
        "latitud": 40.416775,
        "longitud": -3.703790,
        "nombre": "Retiro Park",
        "pais": "Spain"
      }
    },
    "usuariogrupo": {
      "required": [
        "id_usuario",
        "id_grupo"
      ],
      "properties": {
        "id_usuario": {
          "description": "Note:\nThis is a Primary Key.<pk/>\nThis is a Foreign Key to `usuario.id_usuario`.<fk table='usuario' column='id_usuario'/>",
          "format": "integer",
          "type": "integer"
        },
        "id_grupo": {
          "description": "Note:\nThis is a Primary Key.<pk/>\nThis is a Foreign Key to `grupoobservacion.id_grupo`.<fk table='grupoobservacion' column='id_grupo'/>",
          "format": "integer",
          "type": "integer"
        },
        "propietario": {
          "default": false,
          "format": "boolean",
          "type": "boolean"
        },
        "fecha_union": {
          "format": "date",
          "type": "string"
        }
      },
      "type": "object"
    },
    "grupoobservacion": {
      "required": [
        "id_grupo",
        "nombre",
        "fecha_creacion"
      ],
      "properties": {
        "id_grupo": {
          "description": "Note:\nThis is a Primary Key.<pk/>",
          "format": "integer",
          "type": "integer"
        },
        "nombre": {
          "format": "character varying",
          "type": "string"
        },
        "descripcion": {
          "format": "text",
          "type": "string"
        },
        "fecha_creacion": {
          "format": "date",
          "type": "string"
        }
      },
      "type": "object"
    },
    "seguidores": {
      "required": [
        "id_seguidor",
        "id_seguido"
      ],
      "properties": {
        "id_seguidor": {
          "description": "Note:\nThis is a Primary Key.<pk/>\nThis is a Foreign Key to `usuario.id_usuario`.<fk table='usuario' column='id_usuario'/>",
          "format": "integer",
          "type": "integer"
        },
        "id_seguido": {
          "description": "Note:\nThis is a Primary Key.<pk/>\nThis is a Foreign Key to `usuario.id_usuario`.<fk table='usuario' column='id_usuario'/>",
          "format": "integer",
          "type": "integer"
        },
        "fecha_seguimiento": {
          "format": "date",
          "type": "string"
        }
      },
      "type": "object"
    },
    "usuario": {
      "required": [
        "id_usuario",
        "nombre_usuario",
        "email",
        "contrasenia_hash"
      ],
      "properties": {
        "id_usuario": {
          "description": "Note:\nThis is a Primary Key.<pk/>",
          "format": "integer",
          "type": "integer"
        },
        "nombre_usuario": {
          "format": "character varying",
          "type": "string"
        },
        "email": {
          "format": "character varying",
          "type": "string"
        },
        "contrasenia_hash": {
          "format": "character varying",
          "type": "string"
        },
        "url_foto": {
          "format": "character varying",
          "type": "string"
        }
      },
      "type": "object"
    },
    "informacion_meteorologica": {
      "required": ["id_info_meteorologica","id_ubicacion"],
      "properties": {
        "id_info_meteorologica": {
          "description": "Primary key for the weather information record.",
          "format": "integer",
          "type": "integer"
        },
        "id_ubicacion": {
          "description": "Foreign key to ubicacion.id_ubicacion.",
          "format": "integer",
          "type": "integer"
        },
        "temperatura": {
          "description": "Temperature in degrees Celsius (°C).",
          "format": "numeric",
          "type": "number"
        },
        "humedad": {
          "description": "Relative humidity in percent (%). Range: 0-100.",
          "format": "numeric",
          "type": "number"
        },
        "viento": {
          "description": "Wind speed. Specify unit used in your system (m/s or km/h).",
          "format": "numeric",
          "type": "number"
        },
        "nubosidad": {
          "description": "Cloudiness in percent (%).",
          "format": "numeric",
          "type": "number"
        },
        "contaminacion_luminica": {
          "description": "Light pollution value (unit: mag/arcsec² or custom index). Document the unit in your data policy.",
          "format": "numeric",
          "type": "number"
        },
        "indicador_general_sobre_el_cielo": {
          "description": "General sky quality indicator (e.g. scale 0-10).",
          "format": "numeric",
          "type": "number"
        },
        "ultima_actualizacion": {
          "description": "ISO8601 timestamp of the last update (include timezone).",
          "default": "now()",
          "format": "timestamp without time zone",
          "type": "string"
        }
      },
      "type": "object",
      "example": {
        "id_ubicacion": 1,
        "temperatura": 12.3,
        "humedad": 68,
        "viento": 3.4,
        "nubosidad": 20,
        "contaminacion_luminica": 18.5,
        "indicador_general_sobre_el_cielo": 7.8
      }
    },
    "comentario": {
      "required": [
        "id_comentario",
        "id_usuario",
        "id_spot",
        "texto"
      ],
      "properties": {
        "id_comentario": {
          "description": "Note:\nThis is a Primary Key.<pk/>",
          "format": "integer",
          "type": "integer"
        },
        "id_usuario": {
          "description": "Note:\nThis is a Foreign Key to `usuario.id_usuario`.<fk table='usuario' column='id_usuario'/>",
          "format": "integer",
          "type": "integer"
        },
        "id_spot": {
          "description": "Note:\nThis is a Foreign Key to `spot.id_spot`.<fk table='spot' column='id_spot'/>",
          "format": "integer",
          "type": "integer"
        },
        "texto": {
          "format": "text",
          "type": "string"
        },
        "fecha_comentario": {
          "format": "date",
          "type": "string"
        }
      },
      "type": "object"
    },
    "cielo_visible": {
      "required": ["id_cielo_visible","id_ubicacion","tipo","nombre"],
      "properties": {
        "id_cielo_visible": {
          "description": "Primary key for the visible-sky object record.",
          "format": "integer",
          "type": "integer"
        },
        "id_ubicacion": {
          "description": "Foreign key to ubicacion.id_ubicacion.",
          "format": "integer",
          "type": "integer"
        },
        "tipo": {
          "description": "Type of visible object. Example values: 'star','planet','constellation','phenomenon','satellite'.",
          "type": "string",
          "enum": ["star","planet","constellation","phenomenon","satellite"]
        },
        "nombre": {
          "description": "Name or identifier of the object (e.g. 'Jupiter', 'Orion').",
          "type": "string"
        },
        "descripcion": {
          "description": "Free text description with visibility notes and best viewing times.",
          "type": "string"
        },
        "ultima_actualizacion": {
          "description": "ISO8601 timestamp of the last update for this record.",
          "default": "now()",
          "format": "timestamp without time zone",
          "type": "string"
        }
      },
      "type": "object",
      "example": {
        "id_ubicacion": 1,
        "tipo": "planet",
        "nombre": "Jupiter",
        "descripcion": "Visible in the east just after sunset.",
        "ultima_actualizacion": "2025-10-08T21:30:00Z"
      }
    }
    ,
    "alerta": {
      "required": ["id_alerta","id_usuario","tipo_alerta"],
      "properties": {
        "id_alerta": {
          "description": "Primary key for the alerta record.",
          "format": "integer",
          "type": "integer"
        },
        "id_usuario": {
          "description": "Foreign key to usuario.id_usuario (UUID).",
          "format": "uuid",
          "type": "string"
        },
        "id_ubicacion": {
          "description": "Foreign key to ubicacion.id_ubicacion.",
          "format": "integer",
          "type": "integer"
        },
        "tipo_alerta": {
          "description": "Type of alert. Example values: FASE_LUNAR, CONSTELACIONES, EVENTO, PERSONALIZADA.",
          "type": "string",
          "maxLength": 50
        },
        "parametro_objetivo": {
          "description": "Optional parameter for target matching, e.g. 'Waxing Crescent' for lunar phase or a constellation name.",
          "type": "string",
          "maxLength": 100
        },
        "tipo_repeticion": {
          "description": "Repetition type: UNICA, SEMANAL, MENSUAL.",
          "type": "string",
          "maxLength": 20,
          "default": "UNICA",
          "enum": ["UNICA","SEMANAL","MENSUAL"]
        },
        "fecha_objetivo": {
          "description": "Target date for one-time alerts (ISO date yyyy-mm-dd).",
          "format": "date",
          "type": "string"
        },
        "hora_objetivo": {
          "description": "Target time for the alert (HH:MM:SS).",
          "format": "time",
          "type": "string"
        },
        "valor_minimo": {
          "description": "Optional numeric lower bound (example: magnitude).",
          "format": "numeric",
          "type": "number"
        },
        "valor_maximo": {
          "description": "Optional numeric upper bound.",
          "format": "numeric",
          "type": "number"
        },
        "activa": {
          "description": "Whether the alert is active.",
          "type": "boolean",
          "default": true
        },
        "fecha_creacion": {
          "description": "Creation timestamp.",
          "format": "date-time",
          "type": "string"
        },
        "ultima_notificacion": {
          "description": "Timestamp of the last notification sent for this alert.",
          "format": "date-time",
          "type": "string"
        }
      },
      "type": "object",
      "example": {
        "id_alerta": 2,
        "id_usuario": "da8ceff9-3860-483d-ba99-4e8c8b8669d4",
        "id_ubicacion": 57,
        "tipo_alerta": "FASE_LUNAR",
        "parametro_objetivo": "Waxing Crescent",
        "tipo_repeticion": "UNICA",
        "fecha_objetivo": null,
        "hora_objetivo": null,
        "valor_minimo": null,
        "valor_maximo": null,
        "activa": true,
        "fecha_creacion": "2025-10-21T20:23:57",
        "ultima_notificacion": null
      }
    }
  },
  "parameters": {
    "preferParams": {
      "name": "Prefer",
      "description": "Preference",
      "required": false,
      "enum": [],
      "in": "header",
      "type": "string"
    },
    "preferReturn": {
      "name": "Prefer",
      "description": "Preference",
      "required": false,
      "enum": [
        "return=representation",
        "return=minimal",
        "return=none"
      ],
      "in": "header",
      "type": "string"
    },
    "preferCount": {
      "name": "Prefer",
      "description": "Preference",
      "required": false,
      "enum": [
        "count=none"
      ],
      "in": "header",
      "type": "string"
    },
    "preferPost": {
      "name": "Prefer",
      "description": "Preference",
      "required": false,
      "enum": [
        "return=representation",
        "return=minimal",
        "return=none",
        "resolution=ignore-duplicates",
        "resolution=merge-duplicates"
      ],
      "in": "header",
      "type": "string"
    },
    "select": {
      "name": "select",
      "description": "Filtering Columns",
      "required": false,
      "in": "query",
      "type": "string"
    },
    "on_conflict": {
      "name": "on_conflict",
      "description": "On Conflict",
      "required": false,
      "in": "query",
      "type": "string"
    },
    "order": {
      "name": "order",
      "description": "Ordering",
      "required": false,
      "in": "query",
      "type": "string"
    },
    "range": {
      "name": "Range",
      "description": "Limiting and Pagination",
      "required": false,
      "in": "header",
      "type": "string"
    },
    "rangeUnit": {
      "name": "Range-Unit",
      "description": "Limiting and Pagination",
      "required": false,
      "default": "items",
      "in": "header",
      "type": "string"
    },
    "offset": {
      "name": "offset",
      "description": "Limiting and Pagination",
      "required": false,
      "in": "query",
      "type": "string"
    },
    "limit": {
      "name": "limit",
      "description": "Limiting and Pagination",
      "required": false,
      "in": "query",
      "type": "string"
    },
    "body.spot": {
      "name": "spot",
      "description": "spot",
      "required": false,
      "in": "body",
      "schema": {
        "$ref": "#/definitions/spot"
      }
    },
    "rowFilter.spot.id_spot": {
      "name": "id_spot",
      "required": false,
      "in": "query",
      "type": "string"
    },
    "rowFilter.spot.id_usuario_creador": {
      "name": "id_usuario_creador",
      "required": false,
      "in": "query",
      "type": "string"
    },
    "rowFilter.spot.id_ubicacion": {
      "name": "id_ubicacion",
      "required": false,
      "in": "query",
      "type": "string"
    },
    "rowFilter.spot.nombre": {
      "name": "nombre",
      "required": false,
      "in": "query",
      "type": "string"
    },
    "rowFilter.spot.descripcion": {
      "name": "descripcion",
      "required": false,
      "in": "query",
      "type": "string"
    },
    "body.fase_lunar": {
      "name": "fase_lunar",
      "description": "fase_lunar",
      "required": false,
      "in": "body",
      "schema": {
        "$ref": "#/definitions/fase_lunar"
      }
    },
    "rowFilter.fase_lunar.id_luna": {
      "name": "id_luna",
      "required": false,
      "in": "query",
      "type": "string"
    },
    "rowFilter.fase_lunar.id_ubicacion": {
      "name": "id_ubicacion",
      "required": false,
      "in": "query",
      "type": "string"
    },
    "rowFilter.fase_lunar.fase": {
      "name": "fase",
      "required": false,
      "in": "query",
      "type": "string"
    },
    "rowFilter.fase_lunar.porcentaje_iluminacion": {
      "name": "porcentaje_iluminacion",
      "required": false,
      "in": "query",
      "type": "string"
    },
    "rowFilter.fase_lunar.fecha": {
      "name": "fecha",
      "required": false,
      "in": "query",
      "type": "string"
    },
    "body.valoracion": {
      "name": "valoracion",
      "description": "valoracion",
      "required": false,
      "in": "body",
      "schema": {
        "$ref": "#/definitions/valoracion"
      }
    },
    "rowFilter.valoracion.id_usuario": {
      "name": "id_usuario",
      "required": false,
      "in": "query",
      "type": "string"
    },
    "rowFilter.valoracion.id_spot": {
      "name": "id_spot",
      "required": false,
      "in": "query",
      "type": "string"
    },
    "rowFilter.valoracion.puntuacion": {
      "name": "puntuacion",
      "required": false,
      "in": "query",
      "type": "string"
    },
    "rowFilter.valoracion.fecha_valoracion": {
      "name": "fecha_valoracion",
      "required": false,
      "in": "query",
      "type": "string"
    },
    "body.usuarioubicacion": {
      "name": "usuarioubicacion",
      "description": "usuarioubicacion",
      "required": false,
      "in": "body",
      "schema": {
        "$ref": "#/definitions/usuarioubicacion"
      }
    },
    "rowFilter.usuarioubicacion.id_usuario": {
      "name": "id_usuario",
      "required": false,
      "in": "query",
      "type": "string"
    },
    "rowFilter.usuarioubicacion.id_ubicacion": {
      "name": "id_ubicacion",
      "required": false,
      "in": "query",
      "type": "string"
    },
    "rowFilter.usuarioubicacion.fecha_registro": {
      "name": "fecha_registro",
      "required": false,
      "in": "query",
      "type": "string"
    },
    "body.ubicacion": {
      "name": "ubicacion",
      "description": "ubicacion",
      "required": false,
      "in": "body",
      "schema": {
        "$ref": "#/definitions/ubicacion"
      }
    },
    "rowFilter.ubicacion.id_ubicacion": {
      "name": "id_ubicacion",
      "required": false,
      "in": "query",
      "type": "string"
    },
    "rowFilter.ubicacion.latitud": {
      "name": "latitud",
      "required": false,
      "in": "query",
      "type": "string"
    },
    "rowFilter.ubicacion.longitud": {
      "name": "longitud",
      "required": false,
      "in": "query",
      "type": "string"
    },
    "rowFilter.ubicacion.nombre": {
      "name": "nombre",
      "required": false,
      "in": "query",
      "type": "string"
    },
    "rowFilter.ubicacion.pais": {
      "name": "pais",
      "required": false,
      "in": "query",
      "type": "string"
    },
    "body.usuariogrupo": {
      "name": "usuariogrupo",
      "description": "usuariogrupo",
      "required": false,
      "in": "body",
      "schema": {
        "$ref": "#/definitions/usuariogrupo"
      }
    },
    "rowFilter.usuariogrupo.id_usuario": {
      "name": "id_usuario",
      "required": false,
      "in": "query",
      "type": "string"
    },
    "rowFilter.usuariogrupo.id_grupo": {
      "name": "id_grupo",
      "required": false,
      "in": "query",
      "type": "string"
    },
    "rowFilter.usuariogrupo.propietario": {
      "name": "propietario",
      "required": false,
      "in": "query",
      "type": "string"
    },
    "rowFilter.usuariogrupo.fecha_union": {
      "name": "fecha_union",
      "required": false,
      "in": "query",
      "type": "string"
    },
    "body.grupoobservacion": {
      "name": "grupoobservacion",
      "description": "grupoobservacion",
      "required": false,
      "in": "body",
      "schema": {
        "$ref": "#/definitions/grupoobservacion"
      }
    },
    "rowFilter.grupoobservacion.id_grupo": {
      "name": "id_grupo",
      "required": false,
      "in": "query",
      "type": "string"
    },
    "rowFilter.grupoobservacion.nombre": {
      "name": "nombre",
      "required": false,
      "in": "query",
      "type": "string"
    },
    "rowFilter.grupoobservacion.descripcion": {
      "name": "descripcion",
      "required": false,
      "in": "query",
      "type": "string"
    },
    "rowFilter.grupoobservacion.fecha_creacion": {
      "name": "fecha_creacion",
      "required": false,
      "in": "query",
      "type": "string"
    },
    "body.seguidores": {
      "name": "seguidores",
      "description": "seguidores",
      "required": false,
      "in": "body",
      "schema": {
        "$ref": "#/definitions/seguidores"
      }
    },
    "rowFilter.seguidores.id_seguidor": {
      "name": "id_seguidor",
      "required": false,
      "in": "query",
      "type": "string"
    },
    "rowFilter.seguidores.id_seguido": {
      "name": "id_seguido",
      "required": false,
      "in": "query",
      "type": "string"
    },
    "rowFilter.seguidores.fecha_seguimiento": {
      "name": "fecha_seguimiento",
      "required": false,
      "in": "query",
      "type": "string"
    },
    "body.usuario": {
      "name": "usuario",
      "description": "usuario",
      "required": false,
      "in": "body",
      "schema": {
        "$ref": "#/definitions/usuario"
      }
    },
    "rowFilter.usuario.id_usuario": {
      "name": "id_usuario",
      "required": false,
      "in": "query",
      "type": "string"
    },
    "rowFilter.usuario.nombre_usuario": {
      "name": "nombre_usuario",
      "required": false,
      "in": "query",
      "type": "string"
    },
    "rowFilter.usuario.email": {
      "name": "email",
      "required": false,
      "in": "query",
      "type": "string"
    },
    "rowFilter.usuario.contrasenia_hash": {
      "name": "contrasenia_hash",
      "required": false,
      "in": "query",
      "type": "string"
    },
    "rowFilter.usuario.url_foto": {
      "name": "url_foto",
      "required": false,
      "in": "query",
      "type": "string"
    },
    "body.informacion_meteorologica": {
      "name": "informacion_meteorologica",
      "description": "informacion_meteorologica",
      "required": false,
      "in": "body",
      "schema": {
        "$ref": "#/definitions/informacion_meteorologica"
      }
    },
    "rowFilter.informacion_meteorologica.id_info_meteorologica": {
      "name": "id_info_meteorologica",
      "required": false,
      "in": "query",
      "type": "string"
    },
    "rowFilter.informacion_meteorologica.id_ubicacion": {
      "name": "id_ubicacion",
      "required": false,
      "in": "query",
      "type": "string"
    },
    "rowFilter.informacion_meteorologica.temperatura": {
      "name": "temperatura",
      "required": false,
      "in": "query",
      "type": "string"
    },
    "rowFilter.informacion_meteorologica.humedad": {
      "name": "humedad",
      "required": false,
      "in": "query",
      "type": "string"
    },
    "rowFilter.informacion_meteorologica.viento": {
      "name": "viento",
      "required": false,
      "in": "query",
      "type": "string"
    },
    "rowFilter.informacion_meteorologica.nubosidad": {
      "name": "nubosidad",
      "required": false,
      "in": "query",
      "type": "string"
    },
    "rowFilter.informacion_meteorologica.contaminacion_luminica": {
      "name": "contaminacion_luminica",
      "required": false,
      "in": "query",
      "type": "string"
    },
    "rowFilter.informacion_meteorologica.indicador_general_sobre_el_cielo": {
      "name": "indicador_general_sobre_el_cielo",
      "required": false,
      "in": "query",
      "type": "string"
    },
    "rowFilter.informacion_meteorologica.ultima_actualizacion": {
      "name": "ultima_actualizacion",
      "required": false,
      "in": "query",
      "type": "string"
    },
    "body.comentario": {
      "name": "comentario",
      "description": "comentario",
      "required": false,
      "in": "body",
      "schema": {
        "$ref": "#/definitions/comentario"
      }
    },
    "rowFilter.comentario.id_comentario": {
      "name": "id_comentario",
      "required": false,
      "in": "query",
      "type": "string"
    },
    "rowFilter.comentario.id_usuario": {
      "name": "id_usuario",
      "required": false,
      "in": "query",
      "type": "string"
    },
    "rowFilter.comentario.id_spot": {
      "name": "id_spot",
      "required": false,
      "in": "query",
      "type": "string"
    },
    "rowFilter.comentario.texto": {
      "name": "texto",
      "required": false,
      "in": "query",
      "type": "string"
    },
    "rowFilter.comentario.fecha_comentario": {
      "name": "fecha_comentario",
      "required": false,
      "in": "query",
      "type": "string"
    },
    "body.cielo_visible": {
      "name": "cielo_visible",
      "description": "cielo_visible",
      "required": false,
      "in": "body",
      "schema": {
        "$ref": "#/definitions/cielo_visible"
      }
    },
    "rowFilter.cielo_visible.id_cielo_visible": {
      "name": "id_cielo_visible",
      "required": false,
      "in": "query",
      "type": "string"
    },
    "rowFilter.cielo_visible.id_ubicacion": {
      "name": "id_ubicacion",
      "required": false,
      "in": "query",
      "type": "string"
    },
    "rowFilter.cielo_visible.tipo": {
      "name": "tipo",
      "required": false,
      "in": "query",
      "type": "string"
    },
    "rowFilter.cielo_visible.nombre": {
      "name": "nombre",
      "required": false,
      "in": "query",
      "type": "string"
    },
    "rowFilter.cielo_visible.descripcion": {
      "name": "descripcion",
      "required": false,
      "in": "query",
      "type": "string"
    },
    "rowFilter.cielo_visible.ultima_actualizacion": {
      "name": "ultima_actualizacion",
      "required": false,
      "in": "query",
      "type": "string"
    }
    ,
    "body.alerta": {
      "name": "alerta",
      "description": "alerta",
      "required": false,
      "in": "body",
      "schema": {
        "$ref": "#/definitions/alerta"
      }
    },
    "rowFilter.alerta.id_alerta": {
      "name": "id_alerta",
      "required": false,
      "in": "query",
      "type": "string"
    },
    "rowFilter.alerta.id_usuario": {
      "name": "id_usuario",
      "required": false,
      "in": "query",
      "type": "string"
    },
    "rowFilter.alerta.id_ubicacion": {
      "name": "id_ubicacion",
      "required": false,
      "in": "query",
      "type": "string"
    },
    "rowFilter.alerta.tipo_alerta": {
      "name": "tipo_alerta",
      "required": false,
      "in": "query",
      "type": "string"
    },
    "rowFilter.alerta.tipo_repeticion": {
      "name": "tipo_repeticion",
      "required": false,
      "in": "query",
      "type": "string"
    },
    "rowFilter.alerta.activa": {
      "name": "activa",
      "required": false,
      "in": "query",
      "type": "string"
    }
  },
  "externalDocs": {
    "description": "PostgREST Documentation",
    "url": "https://postgrest.org/en/v13/references/api.html"
  }
}
}
}
